sudoku_solver/__init__.py
sudoku_solver/solver.py
rsr45_sudoku_solver-0.1.2.dist-info/LICENCE
rsr45_sudoku_solver-0.1.2.dist-info/METADATA
rsr45_sudoku_solver-0.1.2.dist-info/WHEEL
rsr45_sudoku_solver-0.1.2.dist-info/entry_points.txt
rsr45_sudoku_solver-0.1.2.dist-info/top_level.txt
rsr45_sudoku_solver-0.1.2.dist-info/RECORD
