Metadata-Version: 2.1
Name: rsr45-sudoku-solver
Version: 0.1.2
Summary: A command-line Sudoku solver using a backtracking algorithm.
Home-page: https://github.com/raunaq-rai/Sudoku-Solver-RR.git
Author: Raunaq Rai
Author-email: rsr45@cam.ac.uk
License: UNKNOWN
Platform: UNKNOWN
Classifier: Programming Language :: Python :: 3
Classifier: License :: OSI Approved :: MIT License
Classifier: Operating System :: OS Independent
Requires-Python: >=3.6
License-File: LICENCE
